dash_auto_save_state/__init__.py
dash_auto_save_state/auto_save_state.py
dash_auto_save_state/hooks.py
dash_auto_save_state-0.1.0.dist-info/licenses/LICENSE
dash_auto_save_state-0.1.0.dist-info/METADATA
dash_auto_save_state-0.1.0.dist-info/WHEEL
dash_auto_save_state-0.1.0.dist-info/top_level.txt
dash_auto_save_state-0.1.0.dist-info/RECORD
