Metadata-Version: 2.4
Name: dash-auto-save-state
Version: 0.1.0
Summary: Automatically save and restore Dash component states to prevent data loss
Home-page: https://github.com/Feanor1992/dash-auto-save-state
Author: Artem Liubarski
Author-email: feanor1992@gmail.com
Keywords: dash,plotly,web-app,auto-save,state-management,localStorage,data-persistence,dash-hook,plugin
License-File: LICENSE
Requires-Dist: dash==2.10.0
Requires-Dist: plotly>=5.0.0
Dynamic: author
Dynamic: author-email
Dynamic: description
Dynamic: description-content-type
Dynamic: home-page
Dynamic: keywords
Dynamic: license-file
Dynamic: requires-dist
Dynamic: summary
